LICENSE
MANIFEST.in
README.md
pyproject.toml
requirements.txt
setup.cfg
setup.py
AFAS_pydantic_orm/__init__.py
AFAS_pydantic_orm/main.py
AFAS_pydantic_orm.egg-info/PKG-INFO
AFAS_pydantic_orm.egg-info/SOURCES.txt
AFAS_pydantic_orm.egg-info/dependency_links.txt
AFAS_pydantic_orm.egg-info/requires.txt
AFAS_pydantic_orm.egg-info/top_level.txt
tests/__init__.py
tests/main.py
tests/test_orm_specific_methods.py
tests/test_to_orm_method.py