Metadata-Version: 2.1
Name: AFAS_pydantic_orm
Version: 1.0.0
Summary: CRUD operations on nested SQLAlchemy ORM-models using Pydantic
Home-page: https://github.com/Alexanderkievit/AFAS_Pydantic_ORM
Author: AKievit
Author-email: <alexander.kievit@afas.nl>
Project-URL: Source, https://github.com/Alexanderkievit/AFAS_Pydantic_ORM
Project-URL: Documentation, https://github.com/Alexanderkievit/AFAS_Pydantic_ORM
Project-URL: Tracker, https://github.com/Alexanderkievit/AFAS_Pydantic_ORM/issues
Keywords: python,pydantic,sqlalchemy,ORM,nested,nesting,CRUD
Classifier: Development Status :: 3 - Alpha
Classifier: Intended Audience :: Developers
Classifier: Programming Language :: Python :: 3
Classifier: Operating System :: OS Independent
Classifier: License :: OSI Approved :: MIT License
Classifier: Natural Language :: English
Classifier: Topic :: Software Development :: Libraries :: Python Modules
Classifier: Topic :: Database
Classifier: Topic :: Database :: Database Engines/Servers
Classifier: Topic :: Software Development :: Version Control :: Git
Classifier: Topic :: Software Development :: Testing :: Unit
Classifier: Typing :: Typed
Requires-Python: >=3.8
License-File: LICENSE
Requires-Dist: pydantic>=2.8.0
Requires-Dist: sqlalchemy>=2.0.00
Provides-Extra: dev
Requires-Dist: pytest>=6.2.3; extra == "dev"
Requires-Dist: coverage>=5.5; extra == "dev"
Requires-Dist: flake8>=3.9.1; extra == "dev"
Requires-Dist: black>=20.8; extra == "dev"
Requires-Dist: mypy>=0.812; extra == "dev"
Requires-Dist: pdoc3>=0.9.2; extra == "dev"
